{
  "Users": [
    {
      "id": 0,
      "user": "se.quezadac",
      "password": "sebaquesillo"
    },
    {
      "id": 1,
      "user": "mar.verap",
      "password": "martinlvrg"
    },
    {
      "id": 2,
      "user": "vi.labbe",
      "password": "cocacola"
    }
  ],
  "comunas": [
    {
      "name": "Algarrobo",
      "identifier": "V-1"
    },
    {
      "name": "Cabildo",
      "identifier": "V-2"
    },
    {
      "name": "Calera",
      "identifier": "V-3"
    },
    {
      "name": "Calle Larga",
      "identifier": "V-4"
    },
    {
      "name": "Cartagena",
      "identifier": "V-5"
    },
    {
      "name": "Casablanca",
      "identifier": "V-6"
    },
    {
      "name": "Catemu",
      "identifier": "V-7"
    },
    {
      "name": "Concon",
      "identifier": "V-8"
    },
    {
      "name": "El Quisco",
      "identifier": "V-9"
    },
    {
      "name": "El Tabo",
      "identifier": "V-10"
    },
    {
      "name": "Hijuelas",
      "identifier": "V-11"
    },
    {
      "name": "Isla de Pascua",
      "identifier": "V-12"
    },
    {
      "name": "Juan Fernandez",
      "identifier": "V-13"
    },
    {
      "name": "La Cruz",
      "identifier": "V-14"
    },
    {
      "name": "La Ligua",
      "identifier": "V-15"
    },
    {
      "name": "Limache",
      "identifier": "V-16"
    },
    {
      "name": "Llaillay",
      "identifier": "V-17"
    },
    {
      "name": "Los Andes",
      "identifier": "V-18"
    },
    {
      "name": "Nogales",
      "identifier": "V-19"
    },
    {
      "name": "Olmue",
      "identifier": "V-20"
    },
    {
      "name": "Panquehue",
      "identifier": "V-21"
    },
    {
      "name": "Papudo",
      "identifier": "V-22"
    },
    {
      "name": "Petorca",
      "identifier": "V-23"
    },
    {
      "name": "Puchuncavi",
      "identifier": "V-24"
    },
    {
      "name": "Putaendo",
      "identifier": "V-25"
    },
    {
      "name": "Quillota",
      "identifier": "V-26"
    },
    {
      "name": "Quilpue",
      "identifier": "V-27"
    },
    {
      "name": "Quintero",
      "identifier": "V-28"
    },
    {
      "name": "Rinconada",
      "identifier": "V-29"
    },
    {
      "name": "San Antonio",
      "identifier": "V-30"
    },
    {
      "name": "San Esteban",
      "identifier": "V-31"
    },
    {
      "name": "San Felipe",
      "identifier": "V-32"
    },
    {
      "name": "Santa Maria",
      "identifier": "V-33"
    },
    {
      "name": "Santo Domingo",
      "identifier": "V-34"
    },
    {
      "name": "Valparaiso",
      "identifier": "V-35"
    },
    {
      "name": "Villa Alemana",
      "identifier": "V-36"
    },
    {
      "name": "Viña del Mar",
      "identifier": "V-37"
    },
    {
      "name": "Zapallar",
      "identifier": "V-38"
    }
  ],
  "Viajes": [
    {
      "Direccion": "",
      "Sede": "",
      "VePropio": "",
      "VeTipo": "",
      "id": 0
    },
    {
      "Direccion": {
        "name": "Calle Larga",
        "identifier": "V-4"
      },
      "Sede": {
        "Sede": "Viña del mar"
      },
      "VePropio": {
        "Tiene": "No"
      },
      "VeTipo": {
        "Tipo": "Camioneta"
      },
      "id": 1
    },
    {
      "Direccion": {
        "name": "Calera",
        "identifier": "V-3"
      },
      "Sede": {
        "Sede": "Viña del mar"
      },
      "VePropio": {
        "Tiene": "No"
      },
      "VeTipo": {
        "Tipo": "Camioneta"
      },
      "id": 2
    },
    {
      "Direccion": {
        "name": "Calera",
        "identifier": "V-3"
      },
      "Sede": {
        "Sede": "Viña del mar"
      },
      "VePropio": {
        "Tiene": "No"
      },
      "VeTipo": {
        "Tipo": "Camioneta"
      },
      "id": 3
    },
    {
      "Direccion": {
        "name": "Calera",
        "identifier": "V-3"
      },
      "Sede": {
        "Sede": "Viña del mar"
      },
      "VePropio": {
        "Tiene": "No"
      },
      "VeTipo": {
        "Tipo": "Auto"
      },
      "id": 4
    }
  ]
}